<?xml version="1.0" encoding="UTF-8" standalone="yes"?>
<w:fonts xmlns:mc="http://schemas.openxmlformats.org/markup-compatibility/2006" xmlns:r="http://schemas.openxmlformats.org/officeDocument/2006/relationships" xmlns:w="http://schemas.openxmlformats.org/wordprocessingml/2006/main" xmlns:w14="http://schemas.microsoft.com/office/word/2010/wordml" xmlns:w15="http://schemas.microsoft.com/office/word/2012/wordml" xmlns:w16se="http://schemas.microsoft.com/office/word/2015/wordml/symex" mc:Ignorable="w14 w15 w16se"><w:font w:name="Arial"><w:panose1 w:val="020B0604020202020204"/><w:charset w:val="00"/><w:family w:val="swiss"/><w:pitch w:val="variable"/><w:sig w:usb0="E0002EFF" w:usb1="C000785B" w:usb2="00000009" w:usb3="00000000" w:csb0="000001FF" w:csb1="00000000"/><w:embedRegular r:id="rId1" w:fontKey="{8487C781-22D2-499F-97B1-AD91A0D31918}"/><w:embedBold r:id="rId2" w:fontKey="{83B4BF8A-2304-423F-ABB6-53531BA4B44C}"/></w:font><w:font w:name="Times New Roman"><w:panose1 w:val="02020603050405020304"/><w:charset w:val="00"/><w:family w:val="roman"/><w:pitch w:val="variable"/><w:sig w:usb0="E0002EFF" w:usb1="C000785B" w:usb2="00000009" w:usb3="00000000" w:csb0="000001FF" w:csb1="00000000"/><w:embedRegular r:id="rId3" w:fontKey="{363FC677-58A5-4B05-B921-0309D9871336}"/><w:embedBold r:id="rId4" w:fontKey="{D59BE6BD-9B42-4260-9C30-DE321665116A}"/></w:font></w:fonts>